LICENSE
MANIFEST.in
README.txt
bootstrap.py
buildout.cfg
setup.cfg
setup.py
blockdiagcontrib/__init__.py
blockdiagcontrib/excelhogan.py
blockdiagcontrib/patch.py
blockdiagcontrib_excelhogan.egg-info/PKG-INFO
blockdiagcontrib_excelhogan.egg-info/SOURCES.txt
blockdiagcontrib_excelhogan.egg-info/dependency_links.txt
blockdiagcontrib_excelhogan.egg-info/entry_points.txt
blockdiagcontrib_excelhogan.egg-info/namespace_packages.txt
blockdiagcontrib_excelhogan.egg-info/requires.txt
blockdiagcontrib_excelhogan.egg-info/top_level.txt